{"stats":{"minecraft:killed":{"minecraft:sheep":2,"minecraft:pig":1,"minecraft:cow":1},"minecraft:used":{"minecraft:mutton":2,"minecraft:porkchop":3},"minecraft:custom":{"minecraft:open_chest":4,"minecraft:time_since_rest":6002,"minecraft:crouch_one_cm":454,"minecraft:play_time":6002,"minecraft:sprint_one_cm":23424,"minecraft:damage_taken":63,"minecraft:walk_one_cm":22762,"minecraft:sneak_time":215,"minecraft:walk_under_water_one_cm":874,"minecraft:mob_kills":4,"minecraft:jump":179,"minecraft:damage_dealt":394,"minecraft:leave_game":1,"minecraft:walk_on_water_one_cm":4777,"minecraft:time_since_death":6002,"minecraft:total_world_time":6002,"minecraft:fall_one_cm":5245,"minecraft:fly_one_cm":35777},"minecraft:mined":{"minecraft:hay_block":2,"minecraft:grass":11,"minecraft:sunflower":4,"minecraft:tall_grass":1},"minecraft:picked_up":{"minecraft:leather":1,"minecraft:wheat_seeds":6,"minecraft:hay_block":4,"minecraft:porkchop":3,"minecraft:beef":2,"minecraft:mutton":4,"minecraft:white_wool":2,"minecraft:sunflower":8}},"DataVersion":2975}