{"stats":{"minecraft:killed":{"minecraft:dolphin":1,"minecraft:pig":1},"minecraft:crafted":{"minecraft:bookshelf":12,"minecraft:glass":48,"minecraft:lantern":12,"minecraft:emerald":12,"minecraft:enchanted_book":19,"minecraft:compass":12},"minecraft:custom":{"minecraft:interact_with_anvil":1,"minecraft:mob_kills":2,"minecraft:open_barrel":12,"minecraft:leave_game":11,"minecraft:time_since_death":8443,"minecraft:climb_one_cm":15480,"minecraft:sprint_one_cm":192920,"minecraft:walk_one_cm":1110261,"minecraft:drop":26,"minecraft:talked_to_villager":16,"minecraft:play_time":922726,"minecraft:deaths":1,"minecraft:sneak_time":17478,"minecraft:walk_under_water_one_cm":96374,"minecraft:jump":2737,"minecraft:walk_on_water_one_cm":74956,"minecraft:total_world_time":922726,"minecraft:play_record":23,"minecraft:traded_with_villager":79,"minecraft:tune_noteblock":496,"minecraft:interact_with_loom":10,"minecraft:pot_flower":6,"minecraft:sleep_in_bed":3,"minecraft:time_since_rest":8481,"minecraft:damage_taken":80,"minecraft:damage_dealt":140,"minecraft:fly_one_cm":5357952,"minecraft:open_chest":12,"minecraft:crouch_one_cm":5081,"minecraft:fall_one_cm":1530},"minecraft:used":{"minecraft:oak_trapdoor":7,"minecraft:oak_fence":140,"minecraft:music_disc_far":1,"minecraft:cherry_sapling":3,"minecraft:enchanting_table":2,"minecraft:iron_bars":6,"minecraft:music_disc_otherside":1,"minecraft:flint_and_steel":143,"minecraft:armor_stand":6,"minecraft:spruce_slab":766,"minecraft:ladder":25,"minecraft:diamond_hoe":4,"minecraft:light_gray_carpet":36,"minecraft:chest":33,"minecraft:decorated_pot":3,"minecraft:spruce_planks":997,"minecraft:tinted_glass":11,"minecraft:stone":76,"minecraft:music_disc_5":1,"minecraft:sandstone_wall":164,"minecraft:netherrack":1,"minecraft:brewing_stand":1,"minecraft:dirt":11,"minecraft:anvil":1,"minecraft:red_nether_brick_slab":3,"minecraft:white_carpet":7,"minecraft:brick_slab":12,"minecraft:spruce_stairs":840,"minecraft:cobblestone_wall":20,"minecraft:stone_stairs":6,"minecraft:yellow_carpet":10,"minecraft:music_disc_11":1,"minecraft:music_disc_13":1,"minecraft:spruce_fence":331,"minecraft:oak_fence_gate":17,"minecraft:stripped_spruce_log":310,"minecraft:polished_diorite":262,"minecraft:obsidian":40,"minecraft:music_disc_relic":3,"minecraft:andesite_wall":7,"minecraft:spruce_boat":1,"minecraft:music_disc_mellohi":2,"minecraft:stone_brick_slab":244,"minecraft:netherite_shovel":8,"minecraft:bookshelf":103,"minecraft:villager_spawn_egg":4,"minecraft:music_disc_pigstep":2,"minecraft:spruce_wood":2,"minecraft:lantern":169,"minecraft:grass_block":1041,"minecraft:oak_stairs":7,"minecraft:music_disc_ward":1,"minecraft:brick_stairs":4,"minecraft:smooth_sandstone":775,"minecraft:quartz_block":142,"minecraft:music_disc_chirp":1,"minecraft:netherite_hoe":30,"minecraft:stone_brick_stairs":522,"minecraft:barrel":60,"minecraft:stone_bricks":2312,"minecraft:music_disc_stal":3,"minecraft:spruce_hanging_sign":17,"minecraft:red_carpet":247,"minecraft:redstone_lamp":5,"minecraft:sweet_berries":5,"minecraft:yellow_glazed_terracotta":196,"minecraft:beetroot_seeds":9,"minecraft:cyan_banner":2,"minecraft:orange_terracotta":1,"minecraft:mossy_stone_brick_wall":17,"minecraft:stripped_spruce_wood":131,"minecraft:lime_glazed_terracotta":151,"minecraft:wheat_seeds":17,"minecraft:mossy_stone_bricks":145,"minecraft:water_bucket":135,"minecraft:yellow_banner":45,"minecraft:chiseled_bookshelf":18,"minecraft:diorite":184,"minecraft:cobblestone_stairs":11,"minecraft:dirt_path":581,"minecraft:sandstone_stairs":183,"minecraft:spruce_door":12,"minecraft:birch_planks":5,"minecraft:gray_carpet":1,"minecraft:oak_planks":26,"minecraft:spruce_chest_boat":3,"minecraft:sandstone":249,"minecraft:purple_glazed_terracotta":1,"minecraft:cut_sandstone":310,"minecraft:spruce_fence_gate":62,"minecraft:cobblestone_slab":22,"minecraft:cracked_stone_bricks":11,"minecraft:oak_leaves":50,"minecraft:mossy_cobblestone":15,"minecraft:rail":2,"minecraft:oak_slab":101,"minecraft:sand":1,"minecraft:terracotta":224,"minecraft:netherite_leggings":1,"minecraft:cut_sandstone_slab":100,"minecraft:dark_prismarine_slab":38,"minecraft:loom":5,"minecraft:red_bed":3,"minecraft:smooth_red_sandstone":4,"minecraft:white_bed":2,"minecraft:campfire":13,"minecraft:note_block":19,"minecraft:stone_brick_wall":733,"minecraft:painting":33,"minecraft:end_stone":1,"minecraft:spruce_log":14,"minecraft:music_disc_strad":3,"minecraft:birch_fence":16,"minecraft:oak_log":12,"minecraft:dark_prismarine":6,"minecraft:green_concrete":2,"minecraft:flower_pot":6,"minecraft:black_concrete":2,"minecraft:black_wool":1,"minecraft:music_disc_mall":3,"minecraft:oak_button":74,"minecraft:map":37,"minecraft:stone_slab":26,"minecraft:polished_granite":1,"minecraft:spruce_trapdoor":365,"minecraft:oak_pressure_plate":31,"minecraft:spruce_sapling":2,"minecraft:flowering_azalea_leaves":14,"minecraft:torchflower_seeds":1,"minecraft:cobblestone":5,"minecraft:orange_banner":7,"minecraft:white_banner":1,"minecraft:sandstone_slab":20,"minecraft:red_banner":1,"minecraft:andesite_stairs":17,"minecraft:andesite":39,"minecraft:chain":60,"minecraft:smooth_stone_slab":239,"minecraft:bone_meal":80,"minecraft:smooth_stone":80,"minecraft:jukebox":1},"minecraft:picked_up":{"minecraft:music_disc_5":1,"minecraft:music_disc_strad":2,"minecraft:enchanted_book":10,"minecraft:orange_banner":1,"minecraft:stone_brick_stairs":1,"minecraft:music_disc_otherside":1,"minecraft:poppy":1,"minecraft:stick":3,"minecraft:music_disc_relic":3,"minecraft:torch":2,"minecraft:music_disc_mellohi":1,"minecraft:spruce_fence":1,"minecraft:sandstone_wall":1,"minecraft:porkchop":6,"minecraft:music_disc_11":1,"minecraft:music_disc_pigstep":1,"minecraft:cactus":3,"minecraft:beetroot_seeds":1,"minecraft:music_disc_stal":2,"minecraft:lantern":13,"minecraft:red_carpet":7,"minecraft:kelp":1,"minecraft:wheat_seeds":3,"minecraft:music_disc_far":1,"minecraft:music_disc_chirp":1,"minecraft:sweet_berries":2,"minecraft:music_disc_mall":2,"minecraft:oak_button":2,"minecraft:oak_sapling":1},"minecraft:dropped":{"minecraft:enchanted_book":10,"minecraft:porkchop":6,"minecraft:lantern":1,"minecraft:music_disc_pigstep":1,"minecraft:black_concrete":1,"minecraft:note_block":1,"minecraft:spruce_fence":1,"minecraft:netherite_leggings":1,"minecraft:spruce_wood":1,"minecraft:stone_brick_stairs":1,"minecraft:polished_granite":1,"minecraft:black_wool":1}},"DataVersion":3465}